longalpha_utils/__init__.py
longalpha_utils/constants.py
longalpha_utils/messenger.py
longalpha_utils/transfers.py
longalpha_utils/us_stock_holidays.py
longalpha_utils/utils.py
longalpha_utils-0.64.dist-info/METADATA
longalpha_utils-0.64.dist-info/WHEEL
longalpha_utils-0.64.dist-info/top_level.txt
longalpha_utils-0.64.dist-info/RECORD
