Metadata-Version: 2.1
Name: longalpha-utils
Version: 0.64
Requires-Dist: attrs (==22.2.0)
Requires-Dist: cachetools (==5.3.0)
Requires-Dist: certifi (==2022.12.7)
Requires-Dist: charset-normalizer (==3.0.1)
Requires-Dist: cssselect (==1.2.0)
Requires-Dist: cssutils (==2.6.0)
Requires-Dist: exceptiongroup (==1.1.0)
Requires-Dist: greenlet (==2.0.2)
Requires-Dist: idna (==3.4)
Requires-Dist: iniconfig (==2.0.0)
Requires-Dist: load-dotenv (==0.1.0)
Requires-Dist: lxml (==4.9.2)
Requires-Dist: minio (==7.1.13)
Requires-Dist: numpy (<1.24)
Requires-Dist: packaging (==23.0)
Requires-Dist: pandas (==1.5.3)
Requires-Dist: pluggy (==1.0.0)
Requires-Dist: premailer (==3.10.0)
Requires-Dist: psycopg2-binary (==2.9.5)
Requires-Dist: py4j (==0.10.9.5)
Requires-Dist: pyarrow (==10.0.1)
Requires-Dist: PyJWT (==2.6.0)
Requires-Dist: pyspark (==3.3.1)
Requires-Dist: pytest (==7.2.1)
Requires-Dist: python-dateutil (==2.8.2)
Requires-Dist: python-dotenv (==0.21.1)
Requires-Dist: pytz (==2022.7.1)
Requires-Dist: requests (==2.28.2)
Requires-Dist: six (==1.16.0)
Requires-Dist: slack (==0.0.2)
Requires-Dist: slack-client (==0.3.0)
Requires-Dist: SQLAlchemy (==2.0.3)
Requires-Dist: tomli (==2.0.1)
Requires-Dist: twilio (==7.16.1)
Requires-Dist: typing-extensions (==4.4.0)
Requires-Dist: urllib3 (==1.26.14)
Requires-Dist: yagmail (==0.15.293)
